config/__init__.py
config/config.py
tradehub/__init__.py
tradehub/tradify.py
tradehub/base_validation/__init__.py
tradehub/base_validation/checksum.py
jainam_pytrade_sdk_test-1.0.6.dist-info/METADATA
jainam_pytrade_sdk_test-1.0.6.dist-info/WHEEL
jainam_pytrade_sdk_test-1.0.6.dist-info/top_level.txt
jainam_pytrade_sdk_test-1.0.6.dist-info/RECORD
